dict_zip/__init__.py
dict_zip/_version.py
dict_zip/dict_map.py
dict_zip/dict_zip.py
dict_zip/dict_zip_longest.py
dict_zip/py.typed
dict_zip/tuple_keys.py
dict_zip-0.7.0.dist-info/licenses/LICENSE
dict_zip-0.7.0.dist-info/METADATA
dict_zip-0.7.0.dist-info/WHEEL
dict_zip-0.7.0.dist-info/top_level.txt
dict_zip-0.7.0.dist-info/RECORD
