Metadata-Version: 2.4
Name: dict_zip
Version: 0.7.0
Summary: zip and zip_longest for dict
Author-email: Yui KITSU <kitsuyui+github@kitsuyui.com>
License: Copyright 2019 Kitsu Yui
Project-URL: Homepage, https://github.com/kitsuyui/dict_zip
Classifier: Development Status :: 3 - Alpha
Classifier: License :: OSI Approved :: BSD License
Classifier: Programming Language :: Python :: 3.9
Classifier: Programming Language :: Python :: 3.10
Classifier: Programming Language :: Python :: 3.11
Classifier: Programming Language :: Python :: 3.12
Classifier: Programming Language :: Python :: 3.13
Classifier: Intended Audience :: Developers
Classifier: Topic :: Software Development :: Libraries
Requires-Python: >=3.9
License-File: LICENSE
Dynamic: license-file
